borsodi_database_model/__init__.py
borsodi_database_model/alembic/env.py
borsodi_database_model/alembic/README
borsodi_database_model/alembic/script.py.mako
borsodi_database_model/alembic/versions/0c9e968aeb0b_change_camera_id_enum_values.py
borsodi_database_model/alembic/versions/0d27559e0399_enable_null_for_licence_plate_column_in_.py
borsodi_database_model/alembic/versions/2a4088def437_change_camera_id_column_type_to_integer_.py
borsodi_database_model/alembic/versions/59393fffc97a_add_primary_key_column_to_report_table.py
borsodi_database_model/alembic/versions/5a215d376732_create_truck_tracking_log_table.py
borsodi_database_model/alembic/versions/ce22ee326805_create_report_table.py
borsodi_database_model/alembic/versions/f2f0ad741f61_add_truck_id_column_to_truck_tracking_.py
borsodi_database_model/alembic.ini
borsodi_database_model/tables/__init__.py
borsodi_database_model/tables/base.py
borsodi_database_model/tables/report.py
borsodi_database_model/tables/truck_tracking_log.py
borsodi_database_model-0.4.3.dist-info/WHEEL
borsodi_database_model-0.4.3.dist-info/METADATA
borsodi_database_model-0.4.3.dist-info/RECORD
